fdt/__init__.py
fdt/__main__.py
FirebaseDatabaseTakeover-1.0.1.dist-info/LICENSE
FirebaseDatabaseTakeover-1.0.1.dist-info/METADATA
FirebaseDatabaseTakeover-1.0.1.dist-info/WHEEL
FirebaseDatabaseTakeover-1.0.1.dist-info/entry_points.txt
FirebaseDatabaseTakeover-1.0.1.dist-info/top_level.txt
FirebaseDatabaseTakeover-1.0.1.dist-info/RECORD
