Metadata-Version: 2.1
Name: FirebaseDatabaseTakeover
Version: 1.0.1
Summary: Firebase Database Takeover tool
Author: Akhil Koradiya
Author-email: akhil.koradiya.21@gmail.com
License-File: LICENSE
Requires-Dist: requests
Requires-Dist: colorama
